completejourney_py/__init__.py
completejourney_py/get_data.py
completejourney_py/data/campaign_descriptions.parquet
completejourney_py/data/campaigns.parquet
completejourney_py/data/coupon_redemptions.parquet
completejourney_py/data/coupons.parquet
completejourney_py/data/demographics.parquet
completejourney_py/data/products.parquet
completejourney_py/data/promotions.parquet
completejourney_py/data/transactions.parquet
completejourney_py-0.1.0.dist-info/METADATA
completejourney_py-0.1.0.dist-info/WHEEL
completejourney_py-0.1.0.dist-info/top_level.txt
completejourney_py-0.1.0.dist-info/RECORD
