Metadata-Version: 2.4
Name: completejourney_py
Version: 0.1.0
Summary: Data from R package completejourney
Author-email: James Cunningham <james@notbadafterall.com>, Brad Boehmke <bradleyboehmke@gmail.com>
Maintainer-email: James Cunningham <james@notbadafterall.com>, Brad Boehmke <bradleyboehmke@gmail.com>
License: MIT
Project-URL: Homepage, https://github.com/cunningjames/completejourney_py
Project-URL: Repository, https://github.com/cunningjames/completejourney_py
Project-URL: Issues, https://github.com/cunningjames/completejourney_py/issues
Project-URL: Documentation, https://github.com/cunningjames/completejourney_py
Keywords: data,retail,grocery,transactions,complete journey
Classifier: Development Status :: 4 - Beta
Classifier: Intended Audience :: Developers
Classifier: Intended Audience :: Science/Research
Classifier: Operating System :: OS Independent
Classifier: Programming Language :: Python :: 3
Classifier: Programming Language :: Python :: 3.8
Classifier: Programming Language :: Python :: 3.9
Classifier: Programming Language :: Python :: 3.10
Classifier: Programming Language :: Python :: 3.11
Classifier: Programming Language :: Python :: 3.12
Classifier: Programming Language :: Python :: 3.13
Classifier: Programming Language :: Python :: 3.14
Classifier: Topic :: Scientific/Engineering
Classifier: Topic :: Software Development :: Libraries :: Python Modules
Classifier: Typing :: Typed
Requires-Python: >=3.8
Requires-Dist: pandas>=1.0.0
Requires-Dist: pyarrow>=1.0.0
Requires-Dist: importlib_resources>=1.3.0; python_version < "3.9"
Provides-Extra: dev
Requires-Dist: pytest>=6.0; extra == "dev"
Requires-Dist: flake8>=4.0; extra == "dev"
Requires-Dist: black>=22.0; extra == "dev"
Requires-Dist: isort>=5.0; extra == "dev"
Requires-Dist: mypy>=0.910; extra == "dev"
Requires-Dist: pre-commit>=2.15; extra == "dev"
Provides-Extra: test
Requires-Dist: pytest>=6.0; extra == "test"
Requires-Dist: pytest-cov>=3.0; extra == "test"
Requires-Dist: pytest-xdist>=2.0; extra == "test"
Provides-Extra: docs
Requires-Dist: mkdocs-material>=8.0; extra == "docs"
Requires-Dist: mkdocs-jupyter>=0.21; extra == "docs"
Requires-Dist: mkdocstrings[python]>=0.19; extra == "docs"
Requires-Dist: mkdocs-mermaid2-plugin>=0.6.0; extra == "docs"
Requires-Dist: matplotlib>=3.5; extra == "docs"
Requires-Dist: seaborn>=0.11; extra == "docs"
